seven_api_sdk/.DS_Store
seven_api_sdk/__init__.py
seven_api_sdk-0.1.9.dist-info/WHEEL
seven_api_sdk-0.1.9.dist-info/METADATA
seven_api_sdk-0.1.9.dist-info/RECORD
