Metadata-Version: 2.1
Name: seven-api-sdk
Version: 0.1.9
Summary: A package for end users to use the API endpoints of SEVEN with ease.
License: MIT
Author: Daniel Molnar
Author-email: daniel@prjct8.ch
Requires-Python: >=3.9,<4.0
Classifier: License :: OSI Approved :: MIT License
Classifier: Programming Language :: Python :: 3
Classifier: Programming Language :: Python :: 3.9
Classifier: Programming Language :: Python :: 3.10
Classifier: Programming Language :: Python :: 3.11
Requires-Dist: boto3 (>=1.26.24,<2.0.0)
Requires-Dist: requests (>=2.28.1,<3.0.0)
